{
    "resourceType": "workspaces",
    "apiVersion": "2021-12-01-preview",
    "learnMore": {
        "url": "https://docs.microsoft.com/cli/azure/monitor/log-analytics/workspace"
    },
    "commands": [
        {
            "name": "az monitor log-analytics workspace delete",
            "description": "Deletes a workspace resource.",
            "path": "/subscriptions/{subscriptionId}/resourcegroups/{resourceGroupName}/providers/Microsoft.OperationalInsights/workspaces/{workspaceName}",
            "confirmation": true,
            "help": {
                "learnMore": {
                    "url": "https://docs.microsoft.com/cli/azure/monitor/log-analytics/workspace#az-monitor-log-analytics-workspace-delete"
                },
                "parameterSets": [
                    {
                        "parameters": [
                            "[--resource-group]",
                            "[--subscription]",
                            "[--name]",
                            "[--workspace-name]",
                            "[--force]"
                        ]
                    }
                ]
            },
            "examples": [
                {
                    "description": "Soft delete a workspace instance.",
                    "parameters": [
                        {
                            "name": "--resource-group",
                            "value": "[path.resourceGroupName]"
                        },
                        {
                            "name": "--name",
                            "value": "[path.workspaceName]"
                        },
                        {
                            "name": "--subscription",
                            "value": "[path.subscriptionId]"
                        }
                    ]
                }
            ]
        },
        {
            "name": "az monitor log-analytics workspace get-schema",
            "description": "Get the schema for a given workspace.",
            "path": "/subscriptions/{subscriptionId}/resourcegroups/{resourceGroupName}/providers/Microsoft.OperationalInsights/workspaces/{workspaceName}/schema",
            "confirmation": false,
            "help": {
                "learnMore": {
                    "url": "https://docs.microsoft.com/cli/azure/monitor/log-analytics/workspace#az-monitor-log-analytics-workspace-get-schema"
                },
                "parameterSets": [
                    {
                        "parameters": [
                            "[--resource-group]",
                            "[--subscription]",
                            "[--name]",
                            "[--workspace-name]"
                        ]
                    }
                ]
            },
            "examples": [
                {
                    "description": "Get the schema for a given workspace.",
                    "parameters": [
                        {
                            "name": "--resource-group",
                            "value": "[path.resourceGroupName]"
                        },
                        {
                            "name": "--name",
                            "value": "[path.workspaceName]"
                        },
                        {
                            "name": "--subscription",
                            "value": "[path.subscriptionId]"
                        }
                    ]
                }
            ]
        },
        {
            "name": "az monitor log-analytics workspace get-shared-keys",
            "description": "Get the shared keys for a workspace.",
            "path": "/subscriptions/{subscriptionId}/resourcegroups/{resourceGroupName}/providers/Microsoft.OperationalInsights/workspaces/{workspaceName}/sharedKeys",
            "confirmation": false,
            "help": {
                "learnMore": {
                    "url": "https://docs.microsoft.com/cli/azure/monitor/log-analytics/workspace#az-monitor-log-analytics-workspace-get-shared-keys"
                },
                "parameterSets": [
                    {
                        "parameters": [
                            "[--resource-group]",
                            "[--subscription]",
                            "[--name]",
                            "[--workspace-name]"
                        ]
                    }
                ]
            },
            "examples": [
                {
                    "description": "Get the shared keys for a workspace.",
                    "parameters": [
                        {
                            "name": "--resource-group",
                            "value": "[path.resourceGroupName]"
                        },
                        {
                            "name": "--name",
                            "value": "[path.workspaceName]"
                        },
                        {
                            "name": "--subscription",
                            "value": "[path.subscriptionId]"
                        }
                    ]
                }
            ]
        },
        {
            "name": "az monitor log-analytics workspace list",
            "description": "Get a list of workspaces under a resource group or a subscription.",
            "path": "/subscriptions/{subscriptionId}/resourcegroups/{resourceGroupName}/providers/Microsoft.OperationalInsights/workspaces",
            "confirmation": false,
            "help": {
                "learnMore": {
                    "url": "https://docs.microsoft.com/cli/azure/monitor/log-analytics/workspace#az-monitor-log-analytics-workspace-list"
                },
                "parameterSets": [
                    {
                        "parameters": [
                            "[--resource-group]",
                            "[--subscription]"
                        ]
                    }
                ]
            },
            "examples": [
                {
                    "description": "Get a list of workspaces under a resource group or a subscription.",
                    "parameters": [
                        {
                            "name": "--resource-group",
                            "value": "[path.resourceGroupName]"
                        },
                        {
                            "name": "--subscription",
                            "value": "[path.subscriptionId]"
                        }
                    ]
                }
            ]
        },
        {
            "name": "az monitor log-analytics workspace list-management-groups",
            "description": "Get a list of management groups connected to a workspace.",
            "path": "/subscriptions/{subscriptionId}/resourcegroups/{resourceGroupName}/providers/Microsoft.OperationalInsights/workspaces/{workspaceName}/managementGroups",
            "confirmation": false,
            "help": {
                "learnMore": {
                    "url": "https://docs.microsoft.com/cli/azure/monitor/log-analytics/workspace#az-monitor-log-analytics-workspace-list-management-groups"
                },
                "parameterSets": [
                    {
                        "parameters": [
                            "[--resource-group]",
                            "[--subscription]",
                            "[--name]",
                            "[--workspace-name]"
                        ]
                    }
                ]
            },
            "examples": [
                {
                    "description": "Get a list of management groups connected to a workspace.",
                    "parameters": [
                        {
                            "name": "--resource-group",
                            "value": "[path.resourceGroupName]"
                        },
                        {
                            "name": "--name",
                            "value": "[path.workspaceName]"
                        },
                        {
                            "name": "--subscription",
                            "value": "[path.subscriptionId]"
                        }
                    ]
                }
            ]
        },
        {
            "name": "az monitor log-analytics workspace list-usages",
            "description": "Get a list of usage metrics for a workspace.",
            "path": "/subscriptions/{subscriptionId}/resourcegroups/{resourceGroupName}/providers/Microsoft.OperationalInsights/workspaces/{workspaceName}/usages",
            "confirmation": false,
            "help": {
                "learnMore": {
                    "url": "https://docs.microsoft.com/cli/azure/monitor/log-analytics/workspace#az-monitor-log-analytics-workspace-list-usages"
                },
                "parameterSets": [
                    {
                        "parameters": [
                            "[--resource-group]",
                            "[--subscription]",
                            "[--name]",
                            "[--workspace-name]"
                        ]
                    }
                ]
            },
            "examples": [
                {
                    "description": "Get a list of usage metrics for a workspace.",
                    "parameters": [
                        {
                            "name": "--resource-group",
                            "value": "[path.resourceGroupName]"
                        },
                        {
                            "name": "--name",
                            "value": "[path.workspaceName]"
                        },
                        {
                            "name": "--subscription",
                            "value": "[path.subscriptionId]"
                        }
                    ]
                }
            ]
        },
        {
            "name": "az monitor log-analytics workspace show",
            "description": "Show a workspace instance.",
            "path": "/subscriptions/{subscriptionId}/resourcegroups/{resourceGroupName}/providers/Microsoft.OperationalInsights/workspaces/{workspaceName}",
            "confirmation": false,
            "help": {
                "learnMore": {
                    "url": "https://docs.microsoft.com/cli/azure/monitor/log-analytics/workspace#az-monitor-log-analytics-workspace-show"
                },
                "parameterSets": [
                    {
                        "parameters": [
                            "[--resource-group]",
                            "[--subscription]",
                            "[--name]",
                            "[--workspace-name]"
                        ]
                    }
                ]
            },
            "examples": [
                {
                    "description": "Show a workspace instance.",
                    "parameters": [
                        {
                            "name": "--resource-group",
                            "value": "[path.resourceGroupName]"
                        },
                        {
                            "name": "--name",
                            "value": "[path.workspaceName]"
                        },
                        {
                            "name": "--subscription",
                            "value": "[path.subscriptionId]"
                        }
                    ]
                }
            ]
        },
        {
            "name": "az monitor log-analytics workspace data-export list",
            "description": "List all data export ruleses for a given workspace.",
            "path": "/subscriptions/{subscriptionId}/resourcegroups/{resourceGroupName}/providers/Microsoft.OperationalInsights/workspaces/{workspaceName}/dataExports",
            "confirmation": false,
            "help": {
                "learnMore": {
                    "url": "https://docs.microsoft.com/cli/azure/monitor/log-analytics/workspace/data-export#az-monitor-log-analytics-workspace-data-export-list"
                },
                "parameterSets": [
                    {
                        "parameters": [
                            "[--resource-group]",
                            "[--subscription]",
                            "[--workspace-name]"
                        ]
                    }
                ]
            },
            "examples": [
                {
                    "description": "List all data export ruleses for a given workspace.",
                    "parameters": [
                        {
                            "name": "--resource-group",
                            "value": "[path.resourceGroupName]"
                        },
                        {
                            "name": "--subscription",
                            "value": "[path.subscriptionId]"
                        },
                        {
                            "name": "--workspace-name",
                            "value": "[path.workspaceName]"
                        }
                    ]
                }
            ]
        },
        {
            "name": "az monitor log-analytics workspace linked-service list",
            "description": "Get all the linked services in a workspace.",
            "path": "/subscriptions/{subscriptionId}/resourcegroups/{resourceGroupName}/providers/Microsoft.OperationalInsights/workspaces/{workspaceName}/linkedServices",
            "confirmation": false,
            "help": {
                "learnMore": {
                    "url": "https://docs.microsoft.com/cli/azure/monitor/log-analytics/workspace/linked-service#az-monitor-log-analytics-workspace-linked-service-list"
                },
                "parameterSets": [
                    {
                        "parameters": [
                            "[--resource-group]",
                            "[--subscription]",
                            "[--workspace-name]"
                        ]
                    }
                ]
            },
            "examples": [
                {
                    "description": "Get all the linked services in a workspace.",
                    "parameters": [
                        {
                            "name": "--resource-group",
                            "value": "[path.resourceGroupName]"
                        },
                        {
                            "name": "--workspace-name",
                            "value": "[path.workspaceName]"
                        },
                        {
                            "name": "--subscription",
                            "value": "[path.subscriptionId]"
                        }
                    ]
                }
            ]
        },
        {
            "name": "az monitor log-analytics workspace linked-storage list",
            "description": "List all linked storage accounts for a log analytics workspace.",
            "path": "/subscriptions/{subscriptionId}/resourceGroups/{resourceGroupName}/providers/Microsoft.OperationalInsights/workspaces/{workspaceName}/linkedStorageAccounts",
            "confirmation": false,
            "help": {
                "learnMore": {
                    "url": "https://docs.microsoft.com/cli/azure/monitor/log-analytics/workspace/linked-storage#az-monitor-log-analytics-workspace-linked-storage-list"
                },
                "parameterSets": [
                    {
                        "parameters": [
                            "[--resource-group]",
                            "[--subscription]",
                            "[--workspace-name]"
                        ]
                    }
                ]
            },
            "examples": [
                {
                    "description": "List all linked storage accounts for a log analytics workspace.",
                    "parameters": [
                        {
                            "name": "--resource-group",
                            "value": "[path.resourceGroupName]"
                        },
                        {
                            "name": "--workspace-name",
                            "value": "[path.workspaceName]"
                        },
                        {
                            "name": "--subscription",
                            "value": "[path.subscriptionId]"
                        }
                    ]
                }
            ]
        },
        {
            "name": "az monitor log-analytics workspace pack list",
            "description": "List all the intelligence packs possible and whether they are enabled or disabled for a given workspace.",
            "path": "/subscriptions/{subscriptionId}/resourcegroups/{resourceGroupName}/providers/Microsoft.OperationalInsights/workspaces/{workspaceName}/intelligencePacks",
            "confirmation": false,
            "help": {
                "learnMore": {
                    "url": "https://docs.microsoft.com/cli/azure/monitor/log-analytics/workspace/pack#az-monitor-log-analytics-workspace-pack-list"
                },
                "parameterSets": [
                    {
                        "parameters": [
                            "[--resource-group]",
                            "[--subscription]",
                            "[--workspace-name]"
                        ]
                    }
                ]
            },
            "examples": [
                {
                    "description": "List all the intelligence packs possible and whether they are enabled or disabled for a given workspace.",
                    "parameters": [
                        {
                            "name": "--resource-group",
                            "value": "[path.resourceGroupName]"
                        },
                        {
                            "name": "--workspace-name",
                            "value": "[path.workspaceName]"
                        },
                        {
                            "name": "--subscription",
                            "value": "[path.subscriptionId]"
                        }
                    ]
                }
            ]
        },
        {
            "name": "az monitor log-analytics workspace saved-search list",
            "description": "List all saved searches for a given workspace.",
            "path": "/subscriptions/{subscriptionId}/resourcegroups/{resourceGroupName}/providers/Microsoft.OperationalInsights/workspaces/{workspaceName}/savedSearches",
            "confirmation": false,
            "help": {
                "learnMore": {
                    "url": "https://docs.microsoft.com/cli/azure/monitor/log-analytics/workspace/saved-search#az-monitor-log-analytics-workspace-saved-search-list"
                },
                "parameterSets": [
                    {
                        "parameters": [
                            "[--resource-group]",
                            "[--subscription]",
                            "[--workspace-name]"
                        ]
                    }
                ]
            },
            "examples": [
                {
                    "description": "List all saved searches for a given workspace.",
                    "parameters": [
                        {
                            "name": "--resource-group",
                            "value": "[path.resourceGroupName]"
                        },
                        {
                            "name": "--subscription",
                            "value": "[path.subscriptionId]"
                        },
                        {
                            "name": "--workspace-name",
                            "value": "[path.workspaceName]"
                        }
                    ]
                }
            ]
        },
        {
            "name": "az monitor log-analytics workspace table list",
            "description": "List all the tables for the given Log Analytics workspace.",
            "path": "/subscriptions/{subscriptionId}/resourcegroups/{resourceGroupName}/providers/Microsoft.OperationalInsights/workspaces/{workspaceName}/tables",
            "confirmation": false,
            "help": {
                "learnMore": {
                    "url": "https://docs.microsoft.com/cli/azure/monitor/log-analytics/workspace/table#az-monitor-log-analytics-workspace-table-list"
                },
                "parameterSets": [
                    {
                        "parameters": [
                            "[--resource-group]",
                            "[--subscription]",
                            "[--workspace-name]"
                        ]
                    }
                ]
            },
            "examples": [
                {
                    "description": "List all the tables for the given Log Analytics workspace",
                    "parameters": [
                        {
                            "name": "--resource-group",
                            "value": "[path.resourceGroupName]"
                        },
                        {
                            "name": "--workspace-name",
                            "value": "[path.workspaceName]"
                        },
                        {
                            "name": "--subscription",
                            "value": "[path.subscriptionId]"
                        }
                    ]
                }
            ]
        }
    ]
}